kr_marathon_schedule/__init__.py
kr_marathon_schedule/cli.py
kr_marathon_schedule/scraper.py
kr_marathon_schedule-0.2.0.dist-info/METADATA
kr_marathon_schedule-0.2.0.dist-info/WHEEL
kr_marathon_schedule-0.2.0.dist-info/entry_points.txt
kr_marathon_schedule-0.2.0.dist-info/top_level.txt
kr_marathon_schedule-0.2.0.dist-info/RECORD
