Metadata-Version: 2.4
Name: kr-marathon-schedule
Version: 0.2.0
Summary: A Python package for scraping marathon and running event schedules in Korea with detailed information
Author-email: pilyeooong <pilyeooong@gmail.com>
License: MIT
Project-URL: Homepage, https://github.com/pilyeooong/kr-marathon-schedule
Project-URL: Repository, https://github.com/pilyeooong/kr-marathon-schedule
Project-URL: Issues, https://github.com/pilyeooong/kr-marathon-schedule/issues
Keywords: marathon,running,korea,scraping,schedule
Classifier: Development Status :: 4 - Beta
Classifier: Intended Audience :: Developers
Classifier: License :: OSI Approved :: MIT License
Classifier: Programming Language :: Python :: 3
Classifier: Programming Language :: Python :: 3.8
Classifier: Programming Language :: Python :: 3.9
Classifier: Programming Language :: Python :: 3.10
Classifier: Programming Language :: Python :: 3.11
Classifier: Programming Language :: Python :: 3.12
Classifier: Topic :: Software Development :: Libraries :: Python Modules
Classifier: Topic :: Internet :: WWW/HTTP :: Dynamic Content
Requires-Python: >=3.8
Requires-Dist: beautifulsoup4>=4.12.0
Requires-Dist: requests>=2.25.0
Requires-Dist: certifi>=2021.10.8
Requires-Dist: charset-normalizer>=2.0.0
Requires-Dist: idna>=3.0
Requires-Dist: soupsieve>=2.0
Requires-Dist: urllib3>=1.26.0
Provides-Extra: dev
Requires-Dist: pytest>=6.0; extra == "dev"
Requires-Dist: pytest-cov>=2.0; extra == "dev"
Requires-Dist: black>=22.0; extra == "dev"
Requires-Dist: flake8>=4.0; extra == "dev"
Requires-Dist: mypy>=0.910; extra == "dev"
